docker_containers/__init__.py
docker_containers/container.py
docker_containers/image.py
docker_containers/pg.py
docker_containers/rabbit.py
docker_containers/utils.py
docker_containers-0.0.10.dist-info/METADATA
docker_containers-0.0.10.dist-info/WHEEL
docker_containers-0.0.10.dist-info/top_level.txt
docker_containers-0.0.10.dist-info/RECORD
