Metadata-Version: 2.2
Name: docker_containers
Version: 0.0.10
Summary: Util for start containers
Home-page: https://github.com/PonomarevMaksim/docker-containers
License: BSD
Classifier: Development Status :: 3 - Alpha
Classifier: Environment :: Web Environment
Classifier: Intended Audience :: Developers
Classifier: License :: OSI Approved :: BSD License
Classifier: Operating System :: OS Independent
Classifier: Topic :: Internet :: WWW/HTTP
Classifier: Programming Language :: Python :: 3.7
Requires-Python: >=3.7
Requires-Dist: docker>=7.1
Dynamic: classifier
Dynamic: description
Dynamic: description-content-type
Dynamic: home-page
Dynamic: license
Dynamic: requires-dist
Dynamic: requires-python
Dynamic: summary
